jupyterhub_wordpressauthenticator-0.1.1.dist-info/DESCRIPTION.rst
jupyterhub_wordpressauthenticator-0.1.1.dist-info/METADATA
jupyterhub_wordpressauthenticator-0.1.1.dist-info/RECORD
jupyterhub_wordpressauthenticator-0.1.1.dist-info/WHEEL
jupyterhub_wordpressauthenticator-0.1.1.dist-info/metadata.json
jupyterhub_wordpressauthenticator-0.1.1.dist-info/top_level.txt
wordpressauthenticator/__init__.py
wordpressauthenticator/wordpressauthenticator.py
