Metadata-Version: 2.0
Name: jupyterhub-wordpressauthenticator
Version: 0.1.1
Summary: WordPress Authenticator for JupyterHub
Home-page: https://github.com/harapekoaomushi/jupyterhub-wordpressauthenticator
Author: Harapeko Aomushi
Author-email: harapeko1aomushi@gmail.com
License: MIT License
Keywords: Interactive,Interpreter,Shell,Web
Platform: UNKNOWN
Classifier: Intended Audience :: Developers
Classifier: Intended Audience :: System Administrators
Classifier: Intended Audience :: Science/Research
Classifier: Programming Language :: Python
Classifier: Programming Language :: Python :: 3
Classifier: License :: OSI Approved :: MIT License
Requires-Dist: jupyterhub
Requires-Dist: passlib
Requires-Dist: pymysql
